{
  "metadata": {
    "name": "hentaizhot",
    "author": "B",
    "version": 6,
    "source": "https://hentaiz.hot",
    "regexp": "hentaiz\\.hot\\/watch\\/[^/]+\\/?$",
    "description": "HentaiZ video extension",
    "locale": "vi_VN",
    "language": "javascript",
    "type": "video",
    "tag": "nsfw"
  },
  "script": {
    "home": "home.js",
    "genre": "genre.js",
    "detail": "detail.js",
    "page": "page.js",
    "search": "search.js",
    "suggest": "suggest.js",
    "toc": "toc.js",
    "chap": "chap.js",
    "track": "track.js",
    "comment": "comment.js"
  }
}